django_ftpserver/__init__.py
django_ftpserver/_unix.py
django_ftpserver/_windows.py
django_ftpserver/admin.py
django_ftpserver/authorizers.py
django_ftpserver/daemonizer.py
django_ftpserver/filesystems.py
django_ftpserver/handlers.py
django_ftpserver/models.py
django_ftpserver/server.py
django_ftpserver/signals.py
django_ftpserver/utils.py
django_ftpserver/management/__init__.py
django_ftpserver/management/commands/__init__.py
django_ftpserver/management/commands/createftpuseraccount.py
django_ftpserver/management/commands/createftpusergroup.py
django_ftpserver/management/commands/deleteftpuseraccount.py
django_ftpserver/management/commands/deleteftpusergroup.py
django_ftpserver/management/commands/ftpserver.py
django_ftpserver/management/commands/listftpuseraccount.py
django_ftpserver/management/commands/listftpusergroup.py
django_ftpserver/migrations/0001_initial.py
django_ftpserver/migrations/__init__.py
django_ftpserver-1.0.0.dist-info/licenses/LICENSE
django_ftpserver-1.0.0.dist-info/METADATA
django_ftpserver-1.0.0.dist-info/WHEEL
django_ftpserver-1.0.0.dist-info/top_level.txt
django_ftpserver-1.0.0.dist-info/RECORD
