Metadata-Version: 2.4
Name: django-ftpserver
Version: 1.0.0
Summary: FTP server application for Django.
Author-email: Shinya Okano <tokibito@gmail.com>
License-Expression: MIT
Project-URL: Homepage, https://github.com/tokibito/django-ftpserver
Classifier: Development Status :: 5 - Production/Stable
Classifier: Framework :: Django
Classifier: Programming Language :: Python :: 3.10
Classifier: Programming Language :: Python :: 3.11
Classifier: Programming Language :: Python :: 3.12
Classifier: Programming Language :: Python :: 3.13
Classifier: Programming Language :: Python :: 3.14
License-File: LICENSE
Requires-Dist: Django>=4.2
Requires-Dist: pyftpdlib
Provides-Extra: tls
Requires-Dist: pyOpenSSL; extra == "tls"
Provides-Extra: windows
Requires-Dist: pywin32; extra == "windows"
Provides-Extra: develop
Requires-Dist: pytest; extra == "develop"
Requires-Dist: ruff; extra == "develop"
Requires-Dist: pytest-django; extra == "develop"
Requires-Dist: tox; extra == "develop"
Dynamic: license-file
